Workbook
Name aporte: 'SIMULADOR FII'!$D$10
Name quantidade_anos: 'SIMULADOR FII'!$D$11
Name rendimento_carteira: 'SIMULADOR FII'!$D$6
Name salario: 'SIMULADOR FII'!$B$5
Name sugestao_invest: 'SIMULADOR FII'!$B$7
Name taxa_mensal: 'SIMULADOR FII'!$D$12

Sheet SIMULADOR FII
B4: CONFIGURAÇÕES
B5: Salário | D5: 5000
B6: Rendimento Carteira | D6: 0.01
B7: Sugestão de Investimento (30%) | D7: =D5*30% -> 1500
B9: INVESTIMENTO MENSAL
B10: Quanto investir por mês? | D10: 800
B11: Por quantos anos? | D11: 5
B12: Taxa de Rendimento Mensal? | D12: 0.01079
B13: Patrimônio Acumulado | D13: =FV(taxa_mensal,quantidade_anos*12,aporte*-1) -> 67021.531
B14: Dividendos Mensais | D14: =D13*rendimento_carteira -> 670.21531
B16: CENÁRIOS
B17: PERÍODO | C17: ACUMULADO | D17: DIVIDENDOS
A18: 2 | B18: Quanto em 2 anos? | C18: =FV($D$12,$A18*12,$D$10*-1) -> 21782.102 | D18: =C18*rendimento_carteira -> 217.82102
A19: 5 | B19: Quanto em 5 anos? | C19: =FV($D$12,$A19*12,$D$10*-1) -> 67021.531 | D19: =C19*rendimento_carteira -> 670.21531
A20: 10 | B20: Quanto em 10 anos? | C20: =FV($D$12,$A20*12,$D$10*-1) -> 194627.37 | D20: =C20*rendimento_carteira -> 1946.2737
A21: 20 | B21: Quanto em 20 anos? | C21: =FV($D$12,$A21*12,$D$10*-1) -> 900158.72 | D21: =C21*rendimento_carteira -> 9001.5872
A22: 30 | B22: Quanto em 30 anos? | C22: =FV($D$12,$A22*12,$D$10*-1) -> 3457735.7 | D22: =C22*rendimento_carteira -> 34577.357
B24: PERFIL DE INVESTIDOR | D24: CONSERVADOR
B25: VALOR A SER INVESTIDO POR MÊS | D25: =aporte -> 800
B26: TIPO DE FII | C26: PERCENTUAL SUGERIDO | D26: VALOR
B27: PAPEL | C27: =VLOOKUP($D$24&"-"&B27,'APOIO FII'!$A$1:$D$23,4,FALSE) -> 0.3 | D27: =C27*$D$25 -> 240
B28: TIJOLO | C28: =VLOOKUP($D$24&"-"&B28,'APOIO FII'!$A$1:$D$23,4,FALSE) -> 0.4 | D28: =C28*$D$25 -> 320
B29: HÍBRIDO | C29: =VLOOKUP($D$24&"-"&B29,'APOIO FII'!$A$1:$D$23,4,FALSE) -> 0.1 | D29: =C29*$D$25 -> 80
B30: FOF | C30: =VLOOKUP($D$24&"-"&B30,'APOIO FII'!$A$1:$D$23,4,FALSE) -> 0.1 | D30: =C30*$D$25 -> 80
B31: DESENVOLVIMENTO | C31: =VLOOKUP($D$24&"-"&B31,'APOIO FII'!$A$1:$D$23,4,FALSE) -> 0.05 | D31: =C31*$D$25 -> 40
B32: HOTELARIAS | C32: =VLOOKUP($D$24&"-"&B32,'APOIO FII'!$A$1:$D$23,4,FALSE) -> 0.05 | D32: =C32*$D$25 -> 40
D33: =SUM(D27:D32) -> 800

Sheet APOIO FII
A1: CHAVE | B1: PERFIL | C1: TIPO DE FII | D1: PORCENTAGEM
A2: =B2&"-"&C2 -> CONSERVADOR-PAPEL | B2: CONSERVADOR | C2: PAPEL | D2: 0.3
A3: =B3&"-"&C3 -> CONSERVADOR-TIJOLO | B3: CONSERVADOR | C3: TIJOLO | D3: 0.4
A4: =B4&"-"&C4 -> CONSERVADOR-HÍBRIDO | B4: CONSERVADOR | C4: HÍBRIDO | D4: 0.1
A5: =B5&"-"&C5 -> CONSERVADOR-FOF | B5: CONSERVADOR | C5: FOF | D5: 0.1
A6: =B6&"-"&C6 -> CONSERVADOR-DESENVOLVIMENTO | B6: CONSERVADOR | C6: DESENVOLVIMENTO | D6: 0.05
A7: =B7&"-"&C7 -> CONSERVADOR-HOTELARIAS | B7: CONSERVADOR | C7: HOTELARIAS | D7: 0.05
D8: =SUM(D2:D7) -> 1
A9: CHAVE | B9: PERFIL | C9: TIPO DE FII | D9: PORCENTAGEM
A10: =B10&"-"&C10 -> MODERADO-PAPEL | B10: MODERADO | C10: PAPEL | D10: 0.32
A11: =B11&"-"&C11 -> MODERADO-TIJOLO | B11: MODERADO | C11: TIJOLO | D11: 0.35
A12: =B12&"-"&C12 -> MODERADO-HÍBRIDO | B12: MODERADO | C12: HÍBRIDO | D12: 0.08
A13: =B13&"-"&C13 -> MODERADO-FOF | B13: MODERADO | C13: FOF | D13: 0.05
A14: =B14&"-"&C14 -> MODERADO-DESENVOLVIMENTO | B14: MODERADO | C14: DESENVOLVIMENTO | D14: 0.1
A15: =B15&"-"&C15 -> MODERADO-HOTELARIAS | B15: MODERADO | C15: HOTELARIAS | D15: 0.1
D16: =SUM(D10:D15) -> 1
A17: CHAVE | B17: PERFIL | C17: TIPO DE FII | D17: PORCENTAGEM
A18: =B18&"-"&C18 -> AGRESSIVO-PAPEL | B18: AGRESSIVO | C18: PAPEL | D18: 0.45
A19: =B19&"-"&C19 -> AGRESSIVO-TIJOLO | B19: AGRESSIVO | C19: TIJOLO | D19: 0.15
A20: =B20&"-"&C20 -> AGRESSIVO-HÍBRIDO | B20: AGRESSIVO | C20: HÍBRIDO | D20: 0.05
A21: =B21&"-"&C21 -> AGRESSIVO-FOF | B21: AGRESSIVO | C21: FOF | D21: 0.05
A22: =B22&"-"&C22 -> AGRESSIVO-DESENVOLVIMENTO | B22: AGRESSIVO | C22: DESENVOLVIMENTO | D22: 0.2
A23: =B23&"-"&C23 -> AGRESSIVO-HOTELARIAS | B23: AGRESSIVO | C23: HOTELARIAS | D23: 0.1
D24: =SUM(D18:D23) -> 1
